LICENSE
MANIFEST.in
README.md
setup.cfg
setup.py
scikit_eLCS.egg-info/PKG-INFO
scikit_eLCS.egg-info/SOURCES.txt
scikit_eLCS.egg-info/dependency_links.txt
scikit_eLCS.egg-info/requires.txt
scikit_eLCS.egg-info/top_level.txt
skeLCS/Classifier.py
skeLCS/ClassifierSet.py
skeLCS/DataCleanup.py
skeLCS/DataManagement.py
skeLCS/IterationRecord.py
skeLCS/OfflineEnvironment.py
skeLCS/Prediction.py
skeLCS/Timer.py
skeLCS/__init__.py
skeLCS/eLCS.py
test/__init__.py
test/test_DataCleanup.py
test/test_eLCS.py
test/DataSets/Real/ContinuousAndNonBinaryDiscreteAttributes.csv
test/DataSets/Real/ContinuousAndNonBinaryDiscreteAttributesMissing.csv
test/DataSets/Real/MulticlassPhenotype.csv
test/DataSets/Real/Multiplexer11.csv
test/DataSets/Real/Multiplexer20.csv
test/DataSets/Real/Multiplexer6.csv
test/DataSets/Tests/ContinuousPhenotype.csv
test/DataSets/Tests/MissingFeatureAndPhenotypeData.csv
test/DataSets/Tests/MissingFeatureData.csv
test/DataSets/Tests/StringData.csv
test/DataSets/Tests/StringData2.csv
test/DataSets/Tests/NumericTests/numericFloats.csv
test/DataSets/Tests/NumericTests/numericFloatsMissing.csv
test/DataSets/Tests/NumericTests/numericFloatsNAN.csv
test/DataSets/Tests/NumericTests/numericFloatsString.csv
test/DataSets/Tests/NumericTests/numericInts.csv
test/DataSets/Tests/SpecificityTests/Specifics.csv